{
    "key": "group_64edeaa27a691",
    "title": "Flexible content",
    "fields": [
        {
            "key": "field_64edeab64a4c7",
            "label": "Blocks",
            "name": "blocks",
            "type": "flexible_content",
            "instructions": "",
            "required": 0,
            "conditional_logic": 0,
            "wrapper": {
                "width": "",
                "class": "",
                "id": ""
            },
            "acfe_flexible_advanced": 0,
            "layouts": {
                "layout_64edeac150efe": {
                    "key": "layout_64edeac150efe",
                    "name": "banner",
                    "label": "Banner",
                    "display": "block",
                    "sub_fields": [
                        {
                            "key": "field_64edeadb4a4c8",
                            "label": "Component",
                            "name": "component",
                            "type": "clone",
                            "instructions": "",
                            "required": 0,
                            "conditional_logic": 0,
                            "wrapper": {
                                "width": "",
                                "class": "",
                                "id": ""
                            },
                            "aria-label": "",
                            "clone": [
                                "group_64edea0798e26"
                            ],
                            "display": "seamless",
                            "layout": "block",
                            "prefix_label": 0,
                            "prefix_name": 0,
                            "acfe_seamless_style": 0,
                            "acfe_clone_modal": 0,
                            "acfe_clone_modal_close": 0,
                            "acfe_clone_modal_button": "",
                            "acfe_clone_modal_size": "large"
                        }
                    ],
                    "min": "",
                    "max": "",
                    "acfe_flexible_render_template": false,
                    "acfe_flexible_render_style": false,
                    "acfe_flexible_render_script": false,
                    "acfe_flexible_thumbnail": false,
                    "acfe_flexible_settings": false,
                    "acfe_flexible_settings_size": "medium",
                    "acfe_flexible_modal_edit_size": false,
                    "acfe_flexible_category": false
                },
                "layout_64ee00431e54d": {
                    "key": "layout_64ee00431e54d",
                    "name": "programs",
                    "label": "Programs",
                    "display": "block",
                    "sub_fields": [
                        {
                            "key": "field_64ee004a1e54e",
                            "label": "Component",
                            "name": "component",
                            "type": "clone",
                            "instructions": "",
                            "required": 0,
                            "conditional_logic": 0,
                            "wrapper": {
                                "width": "",
                                "class": "",
                                "id": ""
                            },
                            "aria-label": "",
                            "clone": [
                                "group_64edfd749e419"
                            ],
                            "display": "seamless",
                            "layout": "block",
                            "prefix_label": 0,
                            "prefix_name": 0,
                            "acfe_seamless_style": 0,
                            "acfe_clone_modal": 0,
                            "acfe_clone_modal_close": 0,
                            "acfe_clone_modal_button": "",
                            "acfe_clone_modal_size": "large"
                        }
                    ],
                    "min": "",
                    "max": "",
                    "acfe_flexible_render_template": false,
                    "acfe_flexible_render_style": false,
                    "acfe_flexible_render_script": false,
                    "acfe_flexible_thumbnail": false,
                    "acfe_flexible_settings": false,
                    "acfe_flexible_settings_size": "medium",
                    "acfe_flexible_modal_edit_size": false,
                    "acfe_flexible_category": false
                },
                "layout_64ef0adf0bc6f": {
                    "key": "layout_64ef0adf0bc6f",
                    "name": "image_content",
                    "label": "Image | Content",
                    "display": "block",
                    "sub_fields": [
                        {
                            "key": "field_64ef0aeb0bc70",
                            "label": "Component",
                            "name": "component",
                            "type": "clone",
                            "instructions": "",
                            "required": 0,
                            "conditional_logic": 0,
                            "wrapper": {
                                "width": "",
                                "class": "",
                                "id": ""
                            },
                            "aria-label": "",
                            "clone": [
                                "group_64f59681d6077"
                            ],
                            "display": "seamless",
                            "layout": "",
                            "prefix_label": 0,
                            "prefix_name": 0,
                            "acfe_seamless_style": 0,
                            "acfe_clone_modal": 0,
                            "acfe_clone_modal_close": 0,
                            "acfe_clone_modal_button": "",
                            "acfe_clone_modal_size": "large"
                        }
                    ],
                    "min": "",
                    "max": "",
                    "acfe_flexible_render_template": false,
                    "acfe_flexible_render_style": false,
                    "acfe_flexible_render_script": false,
                    "acfe_flexible_thumbnail": false,
                    "acfe_flexible_settings": false,
                    "acfe_flexible_settings_size": "medium",
                    "acfe_flexible_modal_edit_size": false,
                    "acfe_flexible_category": false
                },
                "layout_64f596f405d47": {
                    "key": "layout_64f596f405d47",
                    "name": "image_text",
                    "label": "Image | Text",
                    "display": "block",
                    "sub_fields": [
                        {
                            "key": "field_64f596f405d48",
                            "label": "Component",
                            "name": "component",
                            "type": "clone",
                            "instructions": "",
                            "required": 0,
                            "conditional_logic": 0,
                            "wrapper": {
                                "width": "",
                                "class": "",
                                "id": ""
                            },
                            "aria-label": "",
                            "clone": [
                                "group_64ef0a36da0b9"
                            ],
                            "display": "seamless",
                            "layout": "block",
                            "prefix_label": 0,
                            "prefix_name": 0,
                            "acfe_seamless_style": 0,
                            "acfe_clone_modal": 0,
                            "acfe_clone_modal_close": 0,
                            "acfe_clone_modal_button": "",
                            "acfe_clone_modal_size": "large"
                        }
                    ],
                    "min": "",
                    "max": "",
                    "acfe_flexible_render_template": false,
                    "acfe_flexible_render_style": false,
                    "acfe_flexible_render_script": false,
                    "acfe_flexible_thumbnail": false,
                    "acfe_flexible_settings": false,
                    "acfe_flexible_settings_size": "medium",
                    "acfe_flexible_modal_edit_size": false,
                    "acfe_flexible_category": false
                },
                "layout_64ef162cafb86": {
                    "key": "layout_64ef162cafb86",
                    "name": "video_blogs",
                    "label": "Video blogs",
                    "display": "block",
                    "sub_fields": [
                        {
                            "key": "field_64ef1637afb87",
                            "label": "Component",
                            "name": "component",
                            "type": "clone",
                            "instructions": "",
                            "required": 0,
                            "conditional_logic": 0,
                            "wrapper": {
                                "width": "",
                                "class": "",
                                "id": ""
                            },
                            "aria-label": "",
                            "clone": [
                                "group_64ef14f8ddd1a"
                            ],
                            "display": "seamless",
                            "layout": "block",
                            "prefix_label": 0,
                            "prefix_name": 0,
                            "acfe_seamless_style": 0,
                            "acfe_clone_modal": 0,
                            "acfe_clone_modal_close": 0,
                            "acfe_clone_modal_button": "",
                            "acfe_clone_modal_size": "large"
                        }
                    ],
                    "min": "",
                    "max": "",
                    "acfe_flexible_render_template": false,
                    "acfe_flexible_render_style": false,
                    "acfe_flexible_render_script": false,
                    "acfe_flexible_thumbnail": false,
                    "acfe_flexible_settings": false,
                    "acfe_flexible_settings_size": "medium",
                    "acfe_flexible_modal_edit_size": false,
                    "acfe_flexible_category": false
                },
                "layout_64ef20517276e": {
                    "key": "layout_64ef20517276e",
                    "name": "clients",
                    "label": "Clients",
                    "display": "block",
                    "sub_fields": [
                        {
                            "key": "field_64f741234e898",
                            "label": "Message",
                            "name": "",
                            "type": "message",
                            "instructions": "",
                            "required": 0,
                            "conditional_logic": 0,
                            "wrapper": {
                                "width": "",
                                "class": "",
                                "id": ""
                            },
                            "aria-label": "",
                            "message": "Nothing to edit here. Please find Information in the left sidebar.\r\n\r\nTheme Options -> Global -> Global blocks -> Clients block",
                            "new_lines": "wpautop",
                            "esc_html": 0
                        }
                    ],
                    "min": "",
                    "max": "",
                    "acfe_flexible_render_template": false,
                    "acfe_flexible_render_style": false,
                    "acfe_flexible_render_script": false,
                    "acfe_flexible_thumbnail": false,
                    "acfe_flexible_settings": false,
                    "acfe_flexible_settings_size": "medium",
                    "acfe_flexible_modal_edit_size": false,
                    "acfe_flexible_category": false
                },
                "layout_64ef50c8a9243": {
                    "key": "layout_64ef50c8a9243",
                    "name": "reviews",
                    "label": "Reviews",
                    "display": "block",
                    "sub_fields": [
                        {
                            "key": "field_64ef50cfa9244",
                            "label": "Component",
                            "name": "component",
                            "type": "clone",
                            "instructions": "",
                            "required": 0,
                            "conditional_logic": 0,
                            "wrapper": {
                                "width": "",
                                "class": "",
                                "id": ""
                            },
                            "aria-label": "",
                            "clone": [
                                "group_64ef42ed54c0f"
                            ],
                            "display": "seamless",
                            "layout": "block",
                            "prefix_label": 0,
                            "prefix_name": 0,
                            "acfe_seamless_style": 0,
                            "acfe_clone_modal": 0,
                            "acfe_clone_modal_close": 0,
                            "acfe_clone_modal_button": "",
                            "acfe_clone_modal_size": "large"
                        }
                    ],
                    "min": "",
                    "max": "",
                    "acfe_flexible_render_template": false,
                    "acfe_flexible_render_style": false,
                    "acfe_flexible_render_script": false,
                    "acfe_flexible_thumbnail": false,
                    "acfe_flexible_settings": false,
                    "acfe_flexible_settings_size": "medium",
                    "acfe_flexible_modal_edit_size": false,
                    "acfe_flexible_category": false
                },
                "layout_64ff113f20dac": {
                    "key": "layout_64ff113f20dac",
                    "name": "contacts",
                    "label": "Contacts",
                    "display": "block",
                    "sub_fields": [
                        {
                            "key": "field_64ff114820dad",
                            "label": "Component",
                            "name": "component",
                            "type": "clone",
                            "instructions": "",
                            "required": 0,
                            "conditional_logic": 0,
                            "wrapper": {
                                "width": "",
                                "class": "",
                                "id": ""
                            },
                            "aria-label": "",
                            "clone": [
                                "group_64ff10495d09f"
                            ],
                            "display": "seamless",
                            "layout": "block",
                            "prefix_label": 0,
                            "prefix_name": 0,
                            "acfe_seamless_style": 0,
                            "acfe_clone_modal": 0,
                            "acfe_clone_modal_close": 0,
                            "acfe_clone_modal_button": "",
                            "acfe_clone_modal_size": "large"
                        }
                    ],
                    "min": "",
                    "max": "",
                    "acfe_flexible_render_template": false,
                    "acfe_flexible_render_style": false,
                    "acfe_flexible_render_script": false,
                    "acfe_flexible_thumbnail": false,
                    "acfe_flexible_settings": false,
                    "acfe_flexible_settings_size": "medium",
                    "acfe_flexible_modal_edit_size": false,
                    "acfe_flexible_category": false
                },
                "layout_6551ebcc5b5d0": {
                    "key": "layout_6551ebcc5b5d0",
                    "name": "color_content_image",
                    "label": "Color-Content | Image",
                    "display": "block",
                    "sub_fields": [
                        {
                            "key": "field_6551ec065b5d1",
                            "label": "Component",
                            "name": "component",
                            "type": "clone",
                            "instructions": "",
                            "required": 0,
                            "conditional_logic": 0,
                            "wrapper": {
                                "width": "",
                                "class": "",
                                "id": ""
                            },
                            "clone": [
                                "group_650b10b54283e"
                            ],
                            "display": "seamless",
                            "layout": "block",
                            "prefix_label": 0,
                            "prefix_name": 0,
                            "acfe_seamless_style": 0,
                            "acfe_clone_modal": 0,
                            "acfe_clone_modal_close": 0,
                            "acfe_clone_modal_button": "",
                            "acfe_clone_modal_size": "large"
                        }
                    ],
                    "min": "",
                    "max": "",
                    "acfe_flexible_render_template": false,
                    "acfe_flexible_render_style": false,
                    "acfe_flexible_render_script": false,
                    "acfe_flexible_thumbnail": false,
                    "acfe_flexible_settings": false,
                    "acfe_flexible_settings_size": "medium",
                    "acfe_flexible_modal_edit_size": false,
                    "acfe_flexible_category": false
                }
            },
            "button_label": "Add Section",
            "min": "",
            "max": "",
            "acfe_flexible_stylised_button": false,
            "acfe_flexible_hide_empty_message": false,
            "acfe_flexible_empty_message": "",
            "acfe_flexible_layouts_templates": false,
            "acfe_flexible_layouts_previews": false,
            "acfe_flexible_layouts_placeholder": false,
            "acfe_flexible_layouts_thumbnails": false,
            "acfe_flexible_layouts_settings": false,
            "acfe_flexible_async": [],
            "acfe_flexible_add_actions": [],
            "acfe_flexible_remove_button": [],
            "acfe_flexible_layouts_state": false,
            "acfe_flexible_modal_edit": {
                "acfe_flexible_modal_edit_enabled": false,
                "acfe_flexible_modal_edit_size": "large"
            },
            "acfe_flexible_modal": {
                "acfe_flexible_modal_enabled": false,
                "acfe_flexible_modal_title": false,
                "acfe_flexible_modal_size": "full",
                "acfe_flexible_modal_col": "4",
                "acfe_flexible_modal_categories": false
            }
        }
    ],
    "location": [
        [
            {
                "param": "post_type",
                "operator": "==",
                "value": "page"
            },
            {
                "param": "page_template",
                "operator": "!=",
                "value": "templates\/graphics-page.php"
            }
        ]
    ],
    "menu_order": 0,
    "position": "normal",
    "style": "default",
    "label_placement": "top",
    "instruction_placement": "label",
    "hide_on_screen": "",
    "active": true,
    "description": "",
    "acfe_display_title": "",
    "acfe_autosync": [
        "json"
    ],
    "acfe_form": 0,
    "acfe_meta": "",
    "acfe_note": "",
    "modified": 1699869706
}